crypto_quant_stat
