Metadata-Version: 2.1
Name: crypto-quant-stat
Version: 0.0.3
Summary: crypto quant stat everyday
Home-page: https://github.com/phamhung3589/crypto_quant_stat.git
Author: hungph
Author-email: phamhung3589@gmail.com
Platform: any
Classifier: Programming Language :: Python :: 3
Classifier: License :: OSI Approved :: MIT License
Classifier: Operating System :: OS Independent
Requires-Python: >=3.6
